dagu_cron_Aditya07/__init__.py
dagu_cron_Aditya07/main.py
dagu_cron-0.1.0.dist-info/LICENSE
dagu_cron-0.1.0.dist-info/METADATA
dagu_cron-0.1.0.dist-info/WHEEL
dagu_cron-0.1.0.dist-info/top_level.txt
dagu_cron-0.1.0.dist-info/RECORD
